<Properties StartupConfiguration="{5B30B77C-F4D9-42C9-9752-DF9A24174F26}|Default">
  <MonoDevelop.Ide.Workbench ActiveDocument="PolynomTests/PolynomTests.cs">
    <Files>
      <File FileName="Polynomial/Program.cs" Line="46" Column="38" />
      <File FileName="Polynomial/Polynom.cs" Line="174" Column="10" />
      <File FileName="PolynomTests/UnitTest1.cs" Line="59" Column="2" />
    </Files>
    <Pads>
      <Pad Id="ProjectPad">
        <State name="__root__">
          <Node name="Polynomial" expanded="True">
            <Node name="Polynomial" expanded="True" />
            <Node name="PolynomialTests" expanded="True">
              <Node name="PolynomTests.cs" selected="True" />
            </Node>
          </Node>
        </State>
      </Pad>
      <Pad Id="MonoDevelop.UnitTesting.TestPad">
        <State name="__root__">
          <Node name="Polynomial" expanded="True">
            <Node name="PolynomialTests" expanded="True">
              <Node name="PolynomialTests" expanded="True">
                <Node name="PolynomTests" expanded="True">
                  <Node name="CheckSubstractionMethod" selected="True" />
                </Node>
              </Node>
            </Node>
          </Node>
        </State>
      </Pad>
    </Pads>
  </MonoDevelop.Ide.Workbench>
  <MonoDevelop.Ide.ItemProperties.Polynomial PreferredExecutionTarget="MonoDevelop.Default" />
  <MonoDevelop.Ide.DebuggingService.PinnedWatches />
  <MonoDevelop.Ide.Workspace ActiveConfiguration="Debug" />
  <MonoDevelop.Ide.DebuggingService.Breakpoints>
    <BreakpointStore />
  </MonoDevelop.Ide.DebuggingService.Breakpoints>
  <MultiItemStartupConfigurations />
</Properties>